KinMSGUITest-0.8.dist-info/METADATA
KinMSGUITest-0.8.dist-info/RECORD
KinMSGUITest-0.8.dist-info/WHEEL
KinMSGUITest-0.8.dist-info/top_level.txt
KinMS_GUI/Clipping.py
KinMS_GUI/GUIFunctions.py
KinMS_GUI/GUI_V0.8.py
KinMS_GUI/KinMS.py
KinMS_GUI/__init__.py
KinMS_GUI/makebeam.py
KinMS_GUI/sauron_colormap.py
